magical_athlete_simulator/.DS_Store
magical_athlete_simulator/__init__.py
magical_athlete_simulator/ai/__init__.py
magical_athlete_simulator/ai/sandbox.py
magical_athlete_simulator/ai/smart_agent.py
magical_athlete_simulator/cli.py
magical_athlete_simulator/core/__init__.py
magical_athlete_simulator/core/abilities.py
magical_athlete_simulator/core/agent.py
magical_athlete_simulator/core/events.py
magical_athlete_simulator/core/mixins.py
magical_athlete_simulator/core/modifiers.py
magical_athlete_simulator/core/registry.py
magical_athlete_simulator/core/state.py
magical_athlete_simulator/core/types.py
magical_athlete_simulator/engine/__init__.py
magical_athlete_simulator/engine/abilities.py
magical_athlete_simulator/engine/board.py
magical_athlete_simulator/engine/flow.py
magical_athlete_simulator/engine/game_engine.py
magical_athlete_simulator/engine/logging.py
magical_athlete_simulator/engine/loop_detection.py
magical_athlete_simulator/engine/movement.py
magical_athlete_simulator/engine/roll.py
magical_athlete_simulator/engine/scenario.py
magical_athlete_simulator/racers/__init__.py
magical_athlete_simulator/racers/baba_yaga.py
magical_athlete_simulator/racers/banana.py
magical_athlete_simulator/racers/centaur.py
magical_athlete_simulator/racers/copycat.py
magical_athlete_simulator/racers/flip_flop.py
magical_athlete_simulator/racers/genius.py
magical_athlete_simulator/racers/gunk.py
magical_athlete_simulator/racers/huge_baby.py
magical_athlete_simulator/racers/magician.py
magical_athlete_simulator/racers/mastermind.py
magical_athlete_simulator/racers/party_animal.py
magical_athlete_simulator/racers/romantic.py
magical_athlete_simulator/racers/scoocher.py
magical_athlete_simulator/racers/skipper.py
magical_athlete_simulator/simulation/__init__.py
magical_athlete_simulator/simulation/combinations.py
magical_athlete_simulator/simulation/config.py
magical_athlete_simulator/simulation/db/__init__.py
magical_athlete_simulator/simulation/db/manager.py
magical_athlete_simulator-0.7.1.dist-info/WHEEL
magical_athlete_simulator-0.7.1.dist-info/entry_points.txt
magical_athlete_simulator-0.7.1.dist-info/METADATA
magical_athlete_simulator-0.7.1.dist-info/RECORD
