Metadata-Version: 2.4
Name: magical-athlete-simulator
Version: 0.7.1
Summary: A simulator for Magical Athlete
Author: Philipp Schoneville
Author-email: Philipp Schoneville <philipp@schoneville.com>
License-Expression: MIT
Requires-Dist: rich>=13.7.1
Requires-Dist: cappa>=0.31.0 ; extra == 'cli'
Requires-Dist: duckdb-engine>=0.17.0 ; extra == 'cli'
Requires-Dist: msgspec>=0.20.0 ; extra == 'cli'
Requires-Dist: sqlmodel>=0.0.31 ; extra == 'cli'
Requires-Dist: tqdm>=4.67.1 ; extra == 'cli'
Requires-Dist: pyarrow>=22.0.0 ; extra == 'cli'
Requires-Dist: marimo==0.18.4 ; extra == 'frontend'
Requires-Dist: altair==6.0.0 ; extra == 'frontend'
Requires-Dist: polars==1.36.1 ; extra == 'frontend'
Requires-Dist: sqlmodel==0.0.31 ; extra == 'frontend'
Requires-Python: ==3.12.7
Project-URL: Changelog, https://github.com/pschonev/magical-athlete-simulator/blob/main/CHANGELOG.md
Project-URL: Repository, https://github.com/pschonev/magical-athlete-simulator
Provides-Extra: cli
Provides-Extra: frontend
